pythoms/__init__.py
pythoms/colour.py
pythoms/progress.py
pythoms/scripttime.py
pythoms/spectrum.py
pythoms/tome.py
pythoms/xlsx.py
pythoms/molecule/__init__.py
pythoms/molecule/_mass_abbreviations.py
pythoms/molecule/_mass_dictionaries.py
pythoms/molecule/base.py
pythoms/molecule/common_losses.py
pythoms/molecule/ip.py
pythoms/molecule/logging.py
pythoms/molecule/mass.py
pythoms/molecule/parsing.py
pythoms/molecule/settings.py
pythoms/molecule/util.py
pythoms/molecule/algorithms/__init__.py
pythoms/molecule/algorithms/bar.py
pythoms/molecule/algorithms/combinatoric.py
pythoms/molecule/algorithms/isospec.py
pythoms/molecule/algorithms/multiplicative.py
pythoms/molecule/algorithms/simulated.py
pythoms/mzml/__init__.py
pythoms/mzml/io.py
pythoms/mzml/logging.py
pythoms/mzml/parsing.py
pythoms/mzml/psi-ms.obo
pythoms/mzml/psims.py
pythoms/mzml/structure.py
pythoms/rsir/__init__.py
pythoms/rsir/data.py
pythoms/rsir/legacy.py
pythoms/rsir/processing.py
tests/__init__.py
tests/test_molecule.py
tests/test_mzml.py
tests/test_pyrsir.py
tests/test_spectrum.py
tests/test_xlsx.py
pythoms-2.2.8.dist-info/LICENSE
pythoms-2.2.8.dist-info/METADATA
pythoms-2.2.8.dist-info/WHEEL
pythoms-2.2.8.dist-info/top_level.txt
pythoms-2.2.8.dist-info/RECORD
